remodnav/__init__.py
remodnav/__main__.py
remodnav/clf.py
remodnav/tests/__init__.py
remodnav/tests/test_detect.py
remodnav/tests/test_labeled.py
remodnav/tests/test_nystrom.py
remodnav/tests/test_preproc.py
remodnav/tests/utils.py
remodnav-1.1.2.dist-info/LICENSE
remodnav-1.1.2.dist-info/METADATA
remodnav-1.1.2.dist-info/WHEEL
remodnav-1.1.2.dist-info/entry_points.txt
remodnav-1.1.2.dist-info/top_level.txt
remodnav-1.1.2.dist-info/RECORD
