Metadata-Version: 2.1
Name: remodnav
Version: 1.1.2
Summary: robust eye movement detection for natural viewing
Home-page: https://github.com/psychoinformatics-de/remodnav
Author: The REMoDNaV Team and Contributors
Author-email: michael.hanke@gmail.com
License: UNKNOWN
Platform: UNKNOWN
Requires-Dist: numpy
Requires-Dist: scipy
Requires-Dist: statsmodels
Requires-Dist: matplotlib
Provides-Extra: devel-docs
Requires-Dist: pypandoc ; extra == 'devel-docs'
